{
  "appId": "410585a9-1914-4b1b-a60f-2b6830a4a486",
  "appIndex": 10,
  "appName": "Klarna: Pagamento inteligente",
  "generatedAt": "2026-07-22T06:09:06.996Z",
  "locale": "ru",
  "markdown": "# Klarna: Pagamento inteligente · Finance\n\nСформировано: 22 июл. 2026 г., 11:09\n\n## **Содержание** {#toc}\n\n- [Баги и стабильность](#theme-bugs_stability)\n- [Цена и paywall](#theme-pricing_paywall)\n\n\n## **Баги и стабильность** {#theme-bugs_stability}\n\n   **Баги и стабильность.**\n      1 свежих отзыв(ов) упоминают: баги и стабильность.\n      Период отзывов: 18 июл. 2026 г. - 18 июл. 2026 г.\n      **Что это значит:** Пользователи жалуются на надежность. Это указывает на quality gap, который может использовать конкурент.\n\n         **Примеры отзывов:**\n            1. _Rishad Mustafaev_, 18 июл. 2026 г., 2/5: \"Новое обновление делает приложение непригодным для использования. Даже на устройстве Pixel 10 производительность вообще ужасная. Новый дизайн Glassy также выглядит дешевым и вводящим в заблуждение. Пожалуйста, верните.\"\n\n## **Цена и paywall** {#theme-pricing_paywall}\n\n   **Цена и paywall.**\n      1 свежих отзыв(ов) упоминают: цена и paywall.\n      Период отзывов: 19 июл. 2026 г. - 19 июл. 2026 г.\n      **Что это значит:** Пользователи упоминают цену, подписку или paywall. Это сигнал чувствительности к монетизации.\n\n         **Примеры отзывов:**\n            1. _keisha keppler_, 19 июл. 2026 г., 5/5: \"Одна из немногих лучших вещей в жизни. Спас и Рождество, и дни рождения, которые случаются не так, как мне удобно. Легко открывается, прост в использовании и является отличным инструментом для дорогого мира, в котором мы живем.\"",
  "nicheSlug": "finance",
  "type": "app"
}
